sigmaepsilon/solid/fem/__init__.py
sigmaepsilon/solid/fem/approximator.py
sigmaepsilon/solid/fem/cells/__init__.py
sigmaepsilon/solid/fem/cells/_bergan80_T3_KL.py
sigmaepsilon/solid/fem/cells/_Q5V.py
sigmaepsilon/solid/fem/cells/allman84.py
sigmaepsilon/solid/fem/cells/andes.py
sigmaepsilon/solid/fem/cells/bergan80_Q4_M.py
sigmaepsilon/solid/fem/cells/bernoulli.py
sigmaepsilon/solid/fem/cells/bernoulli2.py
sigmaepsilon/solid/fem/cells/bernoulli3.py
sigmaepsilon/solid/fem/cells/cook.py
sigmaepsilon/solid/fem/cells/cst.py
sigmaepsilon/solid/fem/cells/gen/b2.py
sigmaepsilon/solid/fem/cells/gen/b3.py
sigmaepsilon/solid/fem/cells/h27.py
sigmaepsilon/solid/fem/cells/h8.py
sigmaepsilon/solid/fem/cells/kirchhoffplate.py
sigmaepsilon/solid/fem/cells/kirchhoffplate4.py
sigmaepsilon/solid/fem/cells/kirchhoffplate9.py
sigmaepsilon/solid/fem/cells/lst.py
sigmaepsilon/solid/fem/cells/mindlin.py
sigmaepsilon/solid/fem/cells/q4.py
sigmaepsilon/solid/fem/cells/q5.py
sigmaepsilon/solid/fem/cells/Q5V.py
sigmaepsilon/solid/fem/cells/q8.py
sigmaepsilon/solid/fem/cells/q9.py
sigmaepsilon/solid/fem/cells/t3_p_KL_eoff.py
sigmaepsilon/solid/fem/cells/t6.py
sigmaepsilon/solid/fem/cells/tet10.py
sigmaepsilon/solid/fem/cells/tet4.py
sigmaepsilon/solid/fem/cells/timoshenko.py
sigmaepsilon/solid/fem/cells/timoshenko2.py
sigmaepsilon/solid/fem/cells/timoshenko3.py
sigmaepsilon/solid/fem/cells/utils/__init__.py
sigmaepsilon/solid/fem/cells/utils/_bergan80_T3_KL.py
sigmaepsilon/solid/fem/cells/utils/all84.py
sigmaepsilon/solid/fem/cells/utils/andes.py
sigmaepsilon/solid/fem/cells/utils/bergan80_Q4_M.py
sigmaepsilon/solid/fem/cells/utils/cook.py
sigmaepsilon/solid/fem/cells/utils/k4p.py
sigmaepsilon/solid/fem/cells/utils/k9p.py
sigmaepsilon/solid/fem/cells/utils/q5.py
sigmaepsilon/solid/fem/cells/utils/super.py
sigmaepsilon/solid/fem/cells/utils/t3_p_KL_eoff.py
sigmaepsilon/solid/fem/cells/wedge.py
sigmaepsilon/solid/fem/config.py
sigmaepsilon/solid/fem/constants.py
sigmaepsilon_solid_fem-1.0.5.dist-info/LICENSE
sigmaepsilon_solid_fem-1.0.5.dist-info/METADATA
sigmaepsilon_solid_fem-1.0.5.dist-info/WHEEL
sigmaepsilon_solid_fem-1.0.5.dist-info/RECORD
