Metadata-Version: 2.1
Name: sigmaepsilon.solid.fem
Version: 1.0.5
Summary: Finite Element Method for Solid Structures in Python.
Home-page: https://github.com/sigma-epsilon/sigmaepsilon.solid.fem
License: MIT
Keywords: engineering,fea,fem,finite element method,mechanics,solid mechanics,optimization,structural analysis,structural engineering,structural optimization,structural simulation,structural design,structural engineering,Python,Python3,Python 3,Python3.10,Python 3.10,Python3.x,Python 3.x
Author: Bence Balogh
Author-email: bencebalogh@sigmaepsilon.com
Maintainer: Bence Balogh
Maintainer-email: bencebalogh@sigmaepsilon.com
Requires-Python: >=3.10,<3.12
Classifier: Development Status :: 5 - Production/Stable
Classifier: License :: OSI Approved :: MIT License
Classifier: Operating System :: OS Independent
Classifier: Programming Language :: Python :: 3
Classifier: Programming Language :: Python :: 3.10
Classifier: Programming Language :: Python :: 3.11
Classifier: Programming Language :: Python :: 3 :: Only
Requires-Dist: sigmaepsilon-mesh (>=2.3.2)
Requires-Dist: sigmaepsilon-solid-material (>=1.0.0,<2.0.0)
Requires-Dist: xarray (>=2024.2.0,<2025.0.0)
Project-URL: Documentation, https://sigmaepsilonsolidfem.readthedocs.io/en/latest/?badge=latest
Project-URL: Repository, https://github.com/sigma-epsilon/sigmaepsilon.solid.fem
